__init__.py
cvxfit.py
cvxfit-0.1.10.dist-info/LICENSE
cvxfit-0.1.10.dist-info/METADATA
cvxfit-0.1.10.dist-info/WHEEL
cvxfit-0.1.10.dist-info/top_level.txt
cvxfit-0.1.10.dist-info/RECORD
