Metadata-Version: 2.1
Name: cvxfit
Version: 0.1.10
Summary: Fit convex approximations to samples of functions
Author-email: Mainak Chowdhury <mainakch@gmail.com>, Alon Kipnis <alon.kipnis@idc.ac.il>, Milind Rao <milind@stanford.edu>
Maintainer-email: Mainak Chowdhury <mainakch@gmail.com>
Project-URL: Homepage, https://github.com/mainakch/cvxfit
Keywords: convex,approximation
Classifier: License :: OSI Approved :: MIT License
Classifier: Programming Language :: Python
Classifier: Programming Language :: Python :: 3
Classifier: Development Status :: 3 - Alpha
Requires-Python: >=3.6
License-File: LICENSE
Requires-Dist: scipy
